LICENSE
MANIFEST.in
README.rst
VERSION
requirements.txt
setup.py
aliyun_ecs.egg-info/PKG-INFO
aliyun_ecs.egg-info/SOURCES.txt
aliyun_ecs.egg-info/dependency_links.txt
aliyun_ecs.egg-info/entry_points.txt
aliyun_ecs.egg-info/requires.txt
aliyun_ecs.egg-info/top_level.txt
ecs/__init__.py
ecs/metadata4vpc.py