Metadata-Version: 1.0
Name: aliyun_ecs
Version: 0.0.5
Summary: A set of simple tools for aliyun ecs.
Home-page: https://github.com/teachmyself/aliyun/ecs
Author: teachmyself
Author-email: teachmyself@126.com
License: MIT LICENSE
Keywords: aliyun,ecs,metadata,vpc,teachmyself
Platform: UNKNOWN
